krolib/__init__.py
krolib/asyncio.py
krolib/parser.py
krolib/structs.py
krolib/utils.py
tests/__init__.py
tests/test_async.py
tests/test_parser.py
krolib-1.2.1.dist-info/LICENSE
krolib-1.2.1.dist-info/METADATA
krolib-1.2.1.dist-info/WHEEL
krolib-1.2.1.dist-info/top_level.txt
krolib-1.2.1.dist-info/RECORD
